phoenix_ml/__init__.py
phoenix_ml/data_preprocessing.py
phoenix_ml/hyperparameter_optimisation.py
phoenix_ml/interpretability.py
phoenix_ml/model_training.py
phoenix_ml/models.py
phoenix_ml/persistence.py
phoenix_ml/physics_model.py
phoenix_ml/postprocessing.py
phoenix_ml/report_generation.py
phoenix_ml/system_info.py
phoenix_ml/uncertainty_quantification.py
phoenix_ml/workflow.py
phoenix_ml_workflow-1.0.1.dist-info/METADATA
phoenix_ml_workflow-1.0.1.dist-info/WHEEL
phoenix_ml_workflow-1.0.1.dist-info/top_level.txt
phoenix_ml_workflow-1.0.1.dist-info/RECORD
