Metadata-Version: 2.4
Name: phoenix_ml_workflow
Version: 1.0.1
Summary: A workflow designed for Physics-Enhanced Machine Learning in engineering applications.
Author-email: "[Ryan Cheung]" <cheungkh@lancaster.ac.uk>
License: MIT
Project-URL: Homepage, https://github.com/Ryan-907316/phoenix_ml
Classifier: Programming Language :: Python :: 3
Classifier: Programming Language :: Python :: 3 :: Only
Classifier: Operating System :: OS Independent
Classifier: Intended Audience :: Science/Research
Classifier: Topic :: Scientific/Engineering :: Artificial Intelligence
Requires-Python: >=3.12.6
Requires-Dist: numpy==1.26.4
Requires-Dist: pandas==2.2.3
Requires-Dist: scipy==1.14.1
Requires-Dist: scikit-learn==1.5.2
Requires-Dist: matplotlib==3.9.2
Requires-Dist: seaborn==0.13.2
Requires-Dist: joblib==1.4.2
Requires-Dist: tqdm==4.66.5
Requires-Dist: tabulate==0.9.0
Requires-Dist: statsmodels==0.14.4
Requires-Dist: scikit-optimize==0.10.2
Requires-Dist: hyperopt==0.2.7
Requires-Dist: dcor==0.6
Requires-Dist: shap==0.46.0
Requires-Dist: reportlab==4.4.3
Requires-Dist: psutil==6.1.0
Requires-Dist: py-cpuinfo==9.0.0
Requires-Dist: xgboost==2.1.2
Requires-Dist: lightgbm==4.5.0
Requires-Dist: pywin32==308; platform_system == "Windows"
